{
    "swagger": "2.0",
    "info": {
        "description": "PNAS 项目 API 文档",
        "title": "PNAS API",
        "contact": {},
        "version": "1.0"
    },
    "host": "localhost:8080",
    "basePath": "/",
    "paths": {
        "/ping": {
            "get": {
                "description": "检查服务是否正常运行",
                "consumes": [
                    "application/json"
                ],
                "produces": [
                    "application/json"
                ],
                "tags": [
                    "健康检查"
                ],
                "summary": "健康检查",
                "responses": {
                    "200": {
                        "description": "OK",
                        "schema": {
                            "$ref": "#/definitions/v1.PingResponse"
                        }
                    }
                }
            }
        }
    },
    "definitions": {
        "v1.PingResponse": {
            "type": "object",
            "properties": {
                "message": {
                    "type": "string",
                    "example": "pong"
                }
            }
        }
    }
}